ixdat/__init__.py
ixdat/config.py
ixdat/constants.py
ixdat/data_series.py
ixdat/db.py
ixdat/exceptions.py
ixdat/measurement_base.py
ixdat/spectra.py
ixdat/tools.py
ixdat/units.py
ixdat/backends/__init__.py
ixdat/backends/backend_base.py
ixdat/backends/directory_backend.py
ixdat/backends/memory_backend.py
ixdat/calculators/__init__.py
ixdat/calculators/ec_calculators.py
ixdat/calculators/ecms_calculators.py
ixdat/calculators/indexer.py
ixdat/calculators/ms_calculators.py
ixdat/calculators/scan_rate_tools.py
ixdat/calculators/xrf_calculators.py
ixdat/exporters/__init__.py
ixdat/exporters/csv_exporter.py
ixdat/exporters/ec_exporter.py
ixdat/exporters/ecms_exporter.py
ixdat/exporters/ms_exporter.py
ixdat/exporters/sec_exporter.py
ixdat/exporters/spectrum_exporter.py
ixdat/plotters/__init__.py
ixdat/plotters/base_mpl_plotter.py
ixdat/plotters/ec_plotter.py
ixdat/plotters/ecms_plotter.py
ixdat/plotters/ms_plotter.py
ixdat/plotters/plotting_tools.py
ixdat/plotters/sec_plotter.py
ixdat/plotters/spectrum_plotter.py
ixdat/plotters/tpms_plotter.py
ixdat/plotters/value_plotter.py
ixdat/plotters/xrf_plotter.py
ixdat/plugins/__init__.py
ixdat/plugins/cinfdata_plugin.py
ixdat/plugins/siq_plugin.py
ixdat/projects/__init__.py
ixdat/projects/lablogs.py
ixdat/projects/samples.py
ixdat/readers/__init__.py
ixdat/readers/autolab.py
ixdat/readers/avantage.py
ixdat/readers/biologic.py
ixdat/readers/chi.py
ixdat/readers/cinfdata.py
ixdat/readers/cinfdata_db.py
ixdat/readers/ec_ms_pkl.py
ixdat/readers/ivium.py
ixdat/readers/ixdat_csv.py
ixdat/readers/msrh_sec.py
ixdat/readers/opus_ftir.py
ixdat/readers/pfeiffer.py
ixdat/readers/qexafs.py
ixdat/readers/reading_tools.py
ixdat/readers/rgasoft.py
ixdat/readers/xrdml.py
ixdat/readers/zilien.py
ixdat/techniques/__init__.py
ixdat/techniques/cv.py
ixdat/techniques/ec.py
ixdat/techniques/ec_ms.py
ixdat/techniques/ftir.py
ixdat/techniques/ms.py
ixdat/techniques/reactor.py
ixdat/techniques/spectroelectrochemistry.py
ixdat/techniques/xrf.py
ixdat-0.3.0.dist-info/LICENSE.txt
ixdat-0.3.0.dist-info/METADATA
ixdat-0.3.0.dist-info/WHEEL
ixdat-0.3.0.dist-info/top_level.txt
ixdat-0.3.0.dist-info/RECORD
