Metadata-Version: 2.1
Name: ixdat
Version: 0.3.0
Summary: The in-situ experimental data tool
Home-page: https://github.com/ixdat/ixdat
Author: Soren B. Scott, Kenneth Nielsen, Anna Winiwarter, et al
Author-email: sbs@chem.ku.dk
License: MIT
Classifier: Programming Language :: Python :: 3
Classifier: License :: OSI Approved :: MIT License
Classifier: Operating System :: OS Independent
Requires-Python: >=3.6
License-File: LICENSE.txt
Requires-Dist: numpy (>=1.16)
Requires-Dist: matplotlib (>=3.2)
Requires-Dist: scipy (>=1.5)
Requires-Dist: mpmath (>=1)
Requires-Dist: pandas (>=1)
